helloworld.py
flashapp-0.0.1.dist-info/LICENSE
flashapp-0.0.1.dist-info/METADATA
flashapp-0.0.1.dist-info/WHEEL
flashapp-0.0.1.dist-info/top_level.txt
flashapp-0.0.1.dist-info/RECORD
